[
  {
    "id": "junkysal",
    "name": "Junkyard Salvager",
    "version": "0.54",
    "description": "You are a lone salvager. Trained to repair and restore the wrecked vessels of the galactic junkyard, you scavenge for parts and resources, to build something out of nothing. Unfortunately, you have more enemies than friends. Captured and robbed of what little you have, you are left stranded on an arid planet. No oxygen. No resources. Just you, your A.I., and a suit constructor.",
    "author": "Teakeycee",
    "lastUpdated": "2025-01-08T09:15:00Z",
    "links": {
      "scenario": "https://steamcommunity.com/sharedfiles/filedetails/?id=3379971469",
      "discord": "https://discord.gg/kWJREUjr2M"
    },
    "hasImage": true,
    "isValid": true,
    "validationErrors": [],
    "source": "remote"
  },
  {
    "id": "re1",
    "name": "Reforged Eden 1",
    "version": "b87",
    "description": "Original Reforged Eden scenario with balanced gameplay and additional content",
    "author": "Vermillion & ravien_ff",
    "lastUpdated": "2024-12-20T15:45:00Z",
    "links": {
      "scenario": "https://steamcommunity.com/sharedfiles/filedetails/?id=2550354956"
    },
    "hasImage": true,
    "isValid": true,
    "validationErrors": [],
    "source": "remote"
  },
  {
    "id": "reforged-eden-2",
    "name": "Reforged Eden 2",
    "version": "b36",
    "description": "Enhanced gameplay with new factions, items, and balance changes",
    "author": "Vermillion & ravien_ff",
    "lastUpdated": "2025-01-15T10:30:00Z",
    "links": {
      "scenario": "https://steamcommunity.com/sharedfiles/filedetails/?id=3143225812"
    },
    "hasImage": true,
    "isValid": true,
    "validationErrors": [],
    "source": "remote"
  },
  {
    "id": "reforged-eden-2",
    "name": "Reforged Eden 2",
    "version": "b44",
    "description": "Reforged Eden 2 is a complete game overhaul that combines Vermillion's Reforged Galaxy 2 and ravien_ff's Project Eden 2 content into a single scenario.",
    "author": "Vermillion & ravien_ff",
    "lastUpdated": "2026-03-18T18:35:00Z",
    "links": {
      "scenario": "https://steamcommunity.com/sharedfiles/filedetails/?id=3143225812"
    },
    "hasImage": false,
    "isValid": true,
    "validationErrors": [],
    "source": "remote"
  },
  {
    "id": "vanilla",
    "name": "Vanilla EGS",
    "version": "1.12.0",
    "description": "Default Empyrion Galactic Survival game scenario with official content",
    "author": "Eleon Game Studios",
    "lastUpdated": "2025-01-10T12:00:00Z",
    "links": {
      "forum": "https://empyriononline.com/"
    },
    "hasImage": true,
    "isValid": true,
    "validationErrors": [],
    "source": "remote"
  },
  {
    "id": "vanilla",
    "name": "Vanilla EGS",
    "version": "1.15",
    "description": "Default Empyrion Galactic Survival game scenario with official content",
    "author": "Eleon Game Studios",
    "lastUpdated": "2026-03-19T12:00:00Z",
    "links": {
      "forum": "https://empyriononline.com/"
    },
    "hasImage": true,
    "isValid": true,
    "validationErrors": [],
    "source": "remote"
  }
]
